permit/__init__.py
permit/config.py
permit/exceptions.py
permit/logger.py
permit/permit.py
permit/sync.py
permit/api/__init__.py
permit/api/api_client.py
permit/api/base.py
permit/api/condition_set_rules.py
permit/api/condition_sets.py
permit/api/context.py
permit/api/deprecated.py
permit/api/elements.py
permit/api/encoders.py
permit/api/environments.py
permit/api/models.py
permit/api/projects.py
permit/api/relationship_tuples.py
permit/api/resource_action_groups.py
permit/api/resource_actions.py
permit/api/resource_attributes.py
permit/api/resource_instances.py
permit/api/resource_relations.py
permit/api/resource_roles.py
permit/api/resources.py
permit/api/role_assignments.py
permit/api/roles.py
permit/api/sync_api_client.py
permit/api/tenants.py
permit/api/user_invites.py
permit/api/users.py
permit/enforcement/__init__.py
permit/enforcement/enforcer.py
permit/enforcement/interfaces.py
permit/pdp_api/__init__.py
permit/pdp_api/base.py
permit/pdp_api/models.py
permit/pdp_api/pdp_api_client.py
permit/pdp_api/role_assignments.py
permit/utils/__init__.py
permit/utils/context.py
permit/utils/deprecation.py
permit/utils/dicts.py
permit/utils/pydantic_version.py
permit/utils/sync.py
tests/__init__.py
tests/conftest.py
tests/test_abac_e2e.py
tests/test_abac_pdp.py
tests/test_rbac_e2e.py
tests/test_rbac_e2e_sync.py
tests/test_rebac_e2e.py
tests/test_sync_client.py
tests/test_user_invites_complete_e2e.py
tests/utils.py
permit-2.8.3.dist-info/LICENSE
permit-2.8.3.dist-info/METADATA
permit-2.8.3.dist-info/WHEEL
permit-2.8.3.dist-info/top_level.txt
permit-2.8.3.dist-info/RECORD
